mw_info/__init__.py
mw_info/agriculture.py
mw_info/currency.py
mw_info/demographics.py
mw_info/health.py
mw_info/mw_info.py
mw_info/data/agriculture_data.yml
mw_info/data/currency_rates.yml
mw_info/data/demographics_data.yml
mw_info/data/district_data.yml
mw_info/data/health_data.yml
mw_info-0.1.2.dist-info/LICENSE
mw_info-0.1.2.dist-info/METADATA
mw_info-0.1.2.dist-info/WHEEL
mw_info-0.1.2.dist-info/top_level.txt
mw_info-0.1.2.dist-info/RECORD
