Metadata-Version: 2.1
Name: mw-info
Version: 0.1.2
Summary: Malawi Information Library (Districts, Currency, Agriculture, Health, Demographics)
Home-page: https://github.com/Tuntufye4/mw-info
Author: Tuntufye Mwanyongo
Author-email: tuntumwanyongo@gmail.com
Classifier: Programming Language :: Python :: 3
Classifier: License :: OSI Approved :: MIT License
Classifier: Operating System :: OS Independent
Requires-Python: >=3.7
License-File: LICENSE
Requires-Dist: PyYAML
